{
  "1": {
    "class_type": "CheckpointLoaderSimple",
    "inputs": {
      "ckpt_name": "__CKPT_NAME__"
    }
  },
  "2": {
    "class_type": "LoadImage",
    "inputs": {
      "image": "__INPUT_IMAGE__"
    }
  },
  "3": {
    "class_type": "CLIPTextEncode",
    "inputs": {
      "text": "__PROMPT__",
      "clip": ["1", 1]
    }
  },
  "4": {
    "class_type": "CLIPTextEncode",
    "inputs": {
      "text": "__NEGATIVE_PROMPT__",
      "clip": ["1", 1]
    }
  },
  "5": {
    "class_type": "VAEEncode",
    "inputs": {
      "pixels": ["2", 0],
      "vae": ["1", 2]
    }
  },
  "6": {
    "class_type": "KSampler",
    "inputs": {
      "seed": __SEED__,
      "steps": __STEPS__,
      "cfg": __CFG__,
      "sampler_name": "__SAMPLER_NAME__",
      "scheduler": "__SCHEDULER__",
      "denoise": __DENOISE__,
      "model": ["1", 0],
      "positive": ["3", 0],
      "negative": ["4", 0],
      "latent_image": ["5", 0]
    }
  },
  "7": {
    "class_type": "VAEDecode",
    "inputs": {
      "samples": ["6", 0],
      "vae": ["1", 2]
    }
  },
  "8": {
    "class_type": "SaveImage",
    "inputs": {
      "filename_prefix": "__OUTPUT_PREFIX__",
      "images": ["7", 0]
    }
  }
}
